minijax/.ipynb_checkpoints/jit-checkpoint.py
minijax/.ipynb_checkpoints/nn-checkpoint.py
minijax/__init__.py
minijax/compute_graph.py
minijax/core.py
minijax/eval.py
minijax/grad.py
minijax/jit.py
minijax/nested_containers.py
minijax/nn.py
minijax/random.py
minijax/vmap.py
minijax-0.1.1.dist-info/WHEEL
minijax-0.1.1.dist-info/METADATA
minijax-0.1.1.dist-info/RECORD
