Metadata-Version: 2.3
Name: minijax
Version: 0.1.1
Summary: A mini machine learning framework a la JAX.
Author: David Boetius
Author-email: David Boetius <david.boetius@uni-konstanz.de>
Requires-Dist: numpy>=2.0,<3.0
Requires-Dist: matplotlib>=3.0,<4.0 ; extra == 'demos'
Requires-Dist: scikit-learn>=1.8.0,<2.0 ; extra == 'demos'
Requires-Dist: jupyter>=1.1,<2.0 ; extra == 'demos'
Requires-Python: >=3.14
Provides-Extra: demos
